ipynb_path/__init__.py
ipynb_path/core.py
ipynb_path-0.1.5.dist-info/WHEEL
ipynb_path-0.1.5.dist-info/METADATA
ipynb_path-0.1.5.dist-info/RECORD
