Metadata-Version: 2.1
Name: ipynb-path
Version: 0.1.5
Summary: A simple python package to get the path of the current IPython / Jupyter Notebook file.
Home-page: https://github.com/kzm4269/ipynb-path
License: MIT
Author: Kazuma Takahara
Author-email: 4269kzm@gmail.com
Requires-Python: >=3.7,<4.0
Classifier: Development Status :: 3 - Alpha
Classifier: Framework :: Jupyter
Classifier: Intended Audience :: End Users/Desktop
Classifier: License :: OSI Approved :: MIT License
Classifier: Programming Language :: Python :: 3
Classifier: Programming Language :: Python :: 3.7
Classifier: Programming Language :: Python :: 3.8
Classifier: Programming Language :: Python :: 3.9
Classifier: Programming Language :: Python :: 3.10
Classifier: Programming Language :: Python :: 3.11
Classifier: Programming Language :: Python :: 3
Classifier: Programming Language :: Python :: 3.7
Classifier: Programming Language :: Python :: 3.8
Classifier: Topic :: Utilities
Requires-Dist: requests (>=2.0,<3.0)
